{"cameraMode":{"drawMode":0,"name":"Shaded","section":"Shading Mode"},"sceneLighting":true,"audioPlay":false,"sceneViewState":{"showFog":true,"showMaterialUpdate":false,"showSkybox":true,"showFlares":true,"showImageEffects":true,"showParticleSystems":true},"in2DMode":false,"pivot":{"x":9.939088821411133,"y":16.051729202270509,"z":57.592369079589847},"rotation":{"x":-0.08965010195970535,"y":0.07104946672916413,"z":0.00641288748010993,"w":0.9934203028678894},"size":38.937442779541019,"orthographic":false}